scaper/__init__.py
scaper/audio.py
scaper/core.py
scaper/scaper_exceptions.py
scaper/scaper_warnings.py
scaper/util.py
scaper/version.py
scaper-1.6.5.dist-info/LICENSE
scaper-1.6.5.dist-info/METADATA
scaper-1.6.5.dist-info/WHEEL
scaper-1.6.5.dist-info/top_level.txt
scaper-1.6.5.dist-info/RECORD
