Metadata-Version: 2.1
Name: scaper
Version: 1.6.5
Summary: A library for soundscape synthesis and augmentation
Home-page: https://github.com/justinsalamon/scaper
Author: Justin Salamon & Duncan MacConnell
Author-email: justin.salamon@gmail.com
License: BSD-3-Clause
Download-URL: http://github.com/justinsalamon/scaper/releases
Keywords: audio sound soundscape environmental dsp mixing
Platform: UNKNOWN
Classifier: License :: OSI Approved :: BSD License
Classifier: Programming Language :: Python
Classifier: Development Status :: 3 - Alpha
Classifier: Intended Audience :: Developers
Classifier: Intended Audience :: Science/Research
Classifier: Topic :: Multimedia :: Sound/Audio :: Analysis
Classifier: Topic :: Multimedia :: Sound/Audio :: Sound Synthesis
Classifier: Programming Language :: Python :: 2
Classifier: Programming Language :: Python :: 2.7
Classifier: Programming Language :: Python :: 3
Classifier: Programming Language :: Python :: 3.4
Classifier: Programming Language :: Python :: 3.5
Classifier: Programming Language :: Python :: 3.6
Requires-Dist: sox (==1.4.0)
Requires-Dist: jams (>=0.3.2)
Requires-Dist: numpy (>=1.13.3)
Requires-Dist: pyloudnorm
Requires-Dist: soundfile
Requires-Dist: soxbindings (>=1.2.2) ; platform_system != "Windows"
Provides-Extra: docs
Requires-Dist: sphinx ; extra == 'docs'
Requires-Dist: sphinx-rtd-theme ; extra == 'docs'
Requires-Dist: sphinx-issues ; extra == 'docs'
Provides-Extra: tests
Requires-Dist: backports.tempfile ; extra == 'tests'
Requires-Dist: pytest ; extra == 'tests'
Requires-Dist: pytest-cov ; extra == 'tests'
Requires-Dist: tqdm ; extra == 'tests'
